{
  "filename": "Organic Materials.pdf",
  "processing_timestamp": "2025-07-06T18:32:29.755611",
  "text_extraction": {
    "success": true,
    "character_count": 2252,
    "output_file": "2_processed_data/text_extracts/Organic Materials.md"
  },
  "table_extraction": {
    "success": true,
    "table_count": 4,
    "output_file": "2_processed_data/table_data/Organic Materials_tables.json",
    "tables_summary": [
      {
        "id": "Organic Materials_table_0",
        "shape": [
          2,
          1
        ],
        "accuracy": 100.0
      },
      {
        "id": "Organic Materials_table_1",
        "shape": [
          2,
          1
        ],
        "accuracy": 100.0
      },
      {
        "id": "Organic Materials_table_2",
        "shape": [
          2,
          1
        ],
        "accuracy": 100.00000000000001
      },
      {
        "id": "Organic Materials_table_3",
        "shape": [
          2,
          1
        ],
        "accuracy": 100.0
      }
    ]
  },
  "quality_metrics": {
    "text_success": true,
    "table_success": true,
    "character_count": 2252,
    "table_count": 4,
    "error_count": 0,
    "processing_completeness": 1.0
  },
  "errors": [],
  "full_text": "## A guide to the total and available phosphate, potash, magnesium and sulphur contents.\n\nfor nitrogen contents and full details see the data source:\n### **AHDB Nutrient Manual (RB209) 2017.**\n\n\n**Potash Development Association**\n**www.pda.org.uk**\n\n\nTypical phosphate, potash, magnesium and sulphur contents in some animal and other organic materials. These can\n\nbe used as default contents in the absence of actual measured or declared values.\n\n\n\n\n\n\n\n\n\n\n\n\n\n\n\n\n\n\n\n\n\n(1) Nutrients available to the next crop (kg/tonne of product, not %).\n\n(2) See back page for sulphur availability.\n\n(3) Potash values will be lower if FYM is stored in the open for long periods.\n\n(4) Adjust nutrient contents if % DM is higher or lower.\n\n\n\n**DM** = Dry matter. **ND** = No data.\nTo convert **kg/t** to **units/ton**, multiply by 2.\nTo convert **kg/m** **[3]** to **units/1000 gallons**, multiply by 9.\n\n\n#### **Sulphur availability from organic materials**\n\nOrganic materials contain valuable amounts of crop-available sulphur and recent research\nhas quantified sulphur supply from livestock manures and biosolids applications. Sulphur\nfrom autumn applications may be lost via overwinter leaching. The quantity leached will\n\ndepend on soil type and overwinter rainfall and is likely to be higher on light textured soils\n\nin high rainfall areas.\n\n\n\n\n\n\n\n\n#### **The importance of laboratory analysis and sampling**\n\nThe nutrient content of organic manures on farms vary widely and so it is better to have\na laboratory analysis carried out to get the correct values specifically for the farm and\nthe year in question. However, it is important that the sample taken for analysis is truly\n\nrepresentative. This means that sampling should be undertaken according to the protocol\n\ngiven in the AHDB Nutrient Management Guide (RB209), Section 2 Organic Manures.\n\n\nIn the absence of a recent analysis, and where thorough sampling can not be done, these\n\ntypical values represent an alternative for nutrient planning purposes.\n\n\n**FOR MORE INFORMATION AND CONTACT DETAILS SEE THE PDA WEBSITE**\n\n\n**www.pda.org.uk**\n\n\n**The Potash Development Association**\nis an independent technical organisation formed\nto support the efficient use of potash fertiliser\nin the UK.\n\n\nMay 2017\n\n\n",
  "table_data": [
    {
      "table_id": "Organic Materials_table_0",
      "page": 2,
      "accuracy": 100.0,
      "data": [
        {
          "0": "Total nutrients\nPhosphate \nPotash \nMagnesium \nSulphur(2) \nMgO\nP2O5\nK2O\nSO3"
        },
        {
          "0": "kg/t"
        }
      ],
      "shape": [
        2,
        1
      ]
    },
    {
      "table_id": "Organic Materials_table_1",
      "page": 2,
      "accuracy": 100.0,
      "data": [
        {
          "0": ""
        },
        {
          "0": "Fresh FYM(3)"
        }
      ],
      "shape": [
        2,
        1
      ]
    },
    {
      "table_id": "Organic Materials_table_2",
      "page": 2,
      "accuracy": 100.00000000000001,
      "data": [
        {
          "0": "Available nutrients(1)\nPhosphate \nPotash \nP2O5\nK2O"
        },
        {
          "0": "kg/t"
        }
      ],
      "shape": [
        2,
        1
      ]
    },
    {
      "table_id": "Organic Materials_table_3",
      "page": 2,
      "accuracy": 100.0,
      "data": [
        {
          "0": "DM"
        },
        {
          "0": "%"
        }
      ],
      "shape": [
        2,
        1
      ]
    }
  ]
}